setup.cfg
setup.py
osimis_broker_helpers/__init__.py
osimis_broker_helpers/brokerHelpers.py
osimis_broker_helpers.egg-info/PKG-INFO
osimis_broker_helpers.egg-info/SOURCES.txt
osimis_broker_helpers.egg-info/dependency_links.txt
osimis_broker_helpers.egg-info/requires.txt
osimis_broker_helpers.egg-info/top_level.txt
osimis_broker_helpers/exceptions/__init__.py
osimis_broker_helpers/exceptions/exceptions.py